sentimetric/__init__.py
sentimetric/sentiment.py
sentimetric-1.0.5.dist-info/licenses/LICENSE
sentimetric-1.0.5.dist-info/METADATA
sentimetric-1.0.5.dist-info/WHEEL
sentimetric-1.0.5.dist-info/entry_points.txt
sentimetric-1.0.5.dist-info/top_level.txt
sentimetric-1.0.5.dist-info/RECORD
