Metadata-Version: 2.4
Name: sentimetric
Version: 1.0.5
Summary: A modern sentiment analysis library with optional LLM support
Home-page: https://github.com/peter-abel/sentimetric
Author: Abel Peter
Author-email: Abel Peter <peterabel791@gmail.com>
License: MIT
Project-URL: Homepage, https://github.com/peter-abel/sentimetric
Project-URL: Documentation, https://github.com/peter-abel/sentimetric#readme
Project-URL: Repository, https://github.com/peter-abel/sentimetric
Project-URL: Bug Tracker, https://github.com/peter-abel/sentimetric/issues
Keywords: sentiment,analysis,nlp,machine-learning,llm,claude
Classifier: Development Status :: 4 - Beta
Classifier: Intended Audience :: Developers
Classifier: Topic :: Text Processing :: Linguistic
Classifier: License :: OSI Approved :: MIT License
Classifier: Programming Language :: Python :: 3
Classifier: Programming Language :: Python :: 3.8
Classifier: Programming Language :: Python :: 3.9
Classifier: Programming Language :: Python :: 3.10
Classifier: Programming Language :: Python :: 3.11
Classifier: Programming Language :: Python :: 3.12
Requires-Python: >=3.8
License-File: LICENSE
Requires-Dist: requests>=2.31.0
Provides-Extra: dev
Requires-Dist: pytest>=7.0.0; extra == "dev"
Requires-Dist: pytest-cov>=4.0.0; extra == "dev"
Requires-Dist: black>=23.0.0; extra == "dev"
Requires-Dist: flake8>=6.0.0; extra == "dev"
Requires-Dist: mypy>=1.0.0; extra == "dev"
Provides-Extra: deepseek
Requires-Dist: openai>=1.0.0; extra == "deepseek"
Dynamic: author
Dynamic: home-page
Dynamic: license-file
Dynamic: requires-python
